reactpy_select/__init__.py
reactpy_select/bundle.dev.js
reactpy_select/bundle.min.js
reactpy_select/bundle_wrapper.py
reactpy_select/select.py
reactpy_select-0.0.5.dist-info/LICENSE
reactpy_select-0.0.5.dist-info/METADATA
reactpy_select-0.0.5.dist-info/WHEEL
reactpy_select-0.0.5.dist-info/RECORD
