Metadata-Version: 2.1
Name: reactpy-select
Version: 0.0.5
Summary: 
Home-page: https://github.com/stevej2608/reactpy-select/blob/master/README.md
License: MIT
Author: Steve Jones
Author-email: jonesst2608@gmail.com
Requires-Python: >=3.9,<4.0.0
Classifier: License :: OSI Approved :: MIT License
Classifier: Programming Language :: Python :: 3
Classifier: Programming Language :: Python :: 3.9
Classifier: Programming Language :: Python :: 3.10
Classifier: Programming Language :: Python :: 3.11
Classifier: Programming Language :: Python :: 3.12
Requires-Dist: reactpy (>=1.0.2,<2.0.0)
Project-URL: Repository, https://github.com/stevej2608/reactpy-select
